mbench/__about__.py
mbench/__init__.py
mbench/profile.py
mbench/test.csv
mbench/test_module.py
mbench/test_profile.csv
mbench/wrapper.py
mbench/tests/test_profile.py
mbench-0.0.11.dist-info/METADATA
mbench-0.0.11.dist-info/WHEEL
mbench-0.0.11.dist-info/entry_points.txt
mbench-0.0.11.dist-info/licenses/LICENSE
mbench-0.0.11.dist-info/licenses/LICENSE.txt
mbench-0.0.11.dist-info/RECORD
